setup.py
east/__init__.py
east/cli.py
east/simple_testbed.py
east/testbed.py
east/toolkit.py
east/trainbed.py
eastkit.egg-info/PKG-INFO
eastkit.egg-info/SOURCES.txt
eastkit.egg-info/dependency_links.txt
eastkit.egg-info/entry_points.txt
eastkit.egg-info/not-zip-safe
eastkit.egg-info/requires.txt
eastkit.egg-info/top_level.txt