Metadata-Version: 1.1
Name: eastkit
Version: 1.0.0
Summary: Emotion and Sentiment Library for Python and Command Line
Home-page: https://github.com/BijoySingh/east
Author: Bijoy Singh Kochar
Author-email: bijoysingh693@gmail.com
License: BSD
Platform: any
Classifier: Development Status :: 5 - Production/Stable
Classifier: Environment :: Console
Classifier: Intended Audience :: Developers
Classifier: License :: OSI Approved :: BSD License
Classifier: Operating System :: POSIX
Classifier: Operating System :: MacOS
Classifier: Operating System :: Unix
Classifier: Operating System :: Microsoft :: Windows
Classifier: Programming Language :: Python
Classifier: Programming Language :: Python :: 2
Classifier: Topic :: Software Development :: Libraries :: Python Modules
